[
  {
    "Event": "50 FR",
    "B": "27.79",
    "BB": "25.69",
    "A": "23.59",
    "AA": "22.49",
    "AAA": "21.39",
    "AAAA": "20.29"
  },
  {
    "Event": "100 FR",
    "B": "1:00.89",
    "BB": "56.19",
    "A": "51.49",
    "AA": "49.09",
    "AAA": "46.79",
    "AAAA": "44.39"
  },
  {
    "Event": "200 FR",
    "B": "2:11.49",
    "BB": "2:01.49",
    "A": "1:51.49",
    "AA": "1:46.49",
    "AAA": "1:41.49",
    "AAAA": "1:36.49"
  },
  {
    "Event": "500 FR",
    "B": "5:56.59",
    "BB": "5:30.89",
    "A": "5:05.19",
    "AA": "4:52.29",
    "AAA": "4:39.49",
    "AAAA": "4:26.59"
  },
  {
    "Event": "1000 FR",
    "B": "12:21.09",
    "BB": "11:25.19",
    "A": "10:29.19",
    "AA": "10:01.29",
    "AAA": "9:33.29",
    "AAAA": "9:05.29"
  },
  {
    "Event": "1650 FR",
    "B": "20:43.09",
    "BB": "19:11.29",
    "A": "17:39.49",
    "AA": "16:53.59",
    "AAA": "16:07.69",
    "AAAA": "15:21.79"
  },
  {
    "Event": "100 BK",
    "B": "1:08.59",
    "BB": "1:03.49",
    "A": "58.49",
    "AA": "55.99",
    "AAA": "53.49",
    "AAAA": "50.99"
  },
  {
    "Event": "200 BK",
    "B": "2:27.89",
    "BB": "2:17.39",
    "A": "2:06.89",
    "AA": "2:01.59",
    "AAA": "1:56.29",
    "AAAA": "1:50.99"
  },
  {
    "Event": "100 BR",
    "B": "1:17.99",
    "BB": "1:12.59",
    "A": "1:07.19",
    "AA": "1:04.49",
    "AAA": "1:01.79",
    "AAAA": "59.09"
  },
  {
    "Event": "200 BR",
    "B": "2:48.39",
    "BB": "2:36.69",
    "A": "2:24.99",
    "AA": "2:19.09",
    "AAA": "2:13.29",
    "AAAA": "2:07.39"
  },
  {
    "Event": "100 FL",
    "B": "1:08.19",
    "BB": "1:03.19",
    "A": "58.19",
    "AA": "55.69",
    "AAA": "53.19",
    "AAAA": "50.69"
  },
  {
    "Event": "200 FL",
    "B": "2:32.49",
    "BB": "2:21.59",
    "A": "2:10.79",
    "AA": "2:05.29",
    "AAA": "1:59.89",
    "AAAA": "1:54.39"
  },
  {
    "Event": "200 IM",
    "B": "2:27.79",
    "BB": "2:17.29",
    "A": "2:06.79",
    "AA": "2:01.49",
    "AAA": "1:56.29",
    "AAAA": "1:50.99"
  },
  {
    "Event": "400 IM",
    "B": "5:14.39",
    "BB": "4:50.99",
    "A": "4:27.59",
    "AA": "4:15.89",
    "AAA": "4:04.19",
    "AAAA": "3:52.49"
  }
]